wbpUFO/__init__.py
wbpUFO/config.py
wbpUFO/document.py
wbpUFO/py.typed
wbpUFO/template.py
wbpUFO/control/__init__.py
wbpUFO/control/dialogItemPicker.py
wbpUFO/control/dialogItemPickerUI.py
wbpUFO/control/findGlyphListCtrl.py
wbpUFO/control/glyphGridStatusPanelUI.py
wbpUFO/control/kerningViewCanvas.py
wbpUFO/control/kerningViewPanelUI.py
wbpUFO/control/libControl.py
wbpUFO/control/panelItemPicker.py
wbpUFO/control/panelItemPickerUI.py
wbpUFO/control/glyphEditor/__init__.py
wbpUFO/control/glyphEditor/canvas.py
wbpUFO/control/glyphEditor/cursor.py
wbpUFO/control/glyphEditor/editPanel.py
wbpUFO/control/glyphEditor/glyphMetricPanel.py
wbpUFO/control/glyphEditor/glyphMetricPanelUI.py
wbpUFO/control/glyphEditor/menu.py
wbpUFO/control/glyphEditor/drawing/__init__.py
wbpUFO/control/glyphEditor/drawing/base.py
wbpUFO/control/glyphEditor/drawing/font.py
wbpUFO/control/glyphEditor/drawing/glyph.py
wbpUFO/control/glyphEditor/tool/__init__.py
wbpUFO/control/glyphEditor/tool/addellipse.py
wbpUFO/control/glyphEditor/tool/addrectangle.py
wbpUFO/control/glyphEditor/tool/base.py
wbpUFO/control/glyphEditor/tool/magicwand.py
wbpUFO/control/glyphEditor/tool/tooldraw.py
wbpUFO/control/glyphEditor/tool/tooledit.py
wbpUFO/control/glyphEditor/tool/toolerase.py
wbpUFO/control/glyphEditor/tool/toolknife.py
wbpUFO/control/glyphEditor/tool/toolmeter.py
wbpUFO/control/glyphEditor/tool/toolpan.py
wbpUFO/control/glyphEditor/tool/toolreverse.py
wbpUFO/control/glyphEditor/tool/toolrotate.py
wbpUFO/control/glyphEditor/tool/toolscale.py
wbpUFO/control/glyphEditor/tool/toolstartpoint.py
wbpUFO/control/glyphEditor/tool/toolzoom.py
wbpUFO/dialog/__init__.py
wbpUFO/dialog/anchorDialog.py
wbpUFO/dialog/anchorDialogUI.py
wbpUFO/dialog/applyGlyphConstructionDialog.py
wbpUFO/dialog/applyGlyphConstructionDialogUI.py
wbpUFO/dialog/assignLayerDialog.py
wbpUFO/dialog/assignLayerDialogUI.py
wbpUFO/dialog/componentDialog.py
wbpUFO/dialog/componentDialogUI.py
wbpUFO/dialog/deleteGlyphsDialog.py
wbpufo-0.2.19.dist-info/licenses/LICENSE
wbpufo-0.2.19.dist-info/METADATA
wbpufo-0.2.19.dist-info/WHEEL
wbpufo-0.2.19.dist-info/entry_points.txt
wbpufo-0.2.19.dist-info/top_level.txt
wbpufo-0.2.19.dist-info/RECORD
