Metadata-Version: 2.4
Name: wbpUFO
Version: 0.2.19
Summary: UFO font editor for Workbench applications.
Home-page: https://gitlab.com/workbench2/workbench-plugins/wbpUFO
Author: Andreas Eigendorf
License: MIT
Project-URL: Source, https://gitlab.com/workbench2/workbench-plugins/wbpUFO
Project-URL: Documentation, https://workbench2.gitlab.io/workbench-plugins/wbpUFO
Project-URL: Tracker, https://gitlab.com/workbench2/workbench-plugins/wbpUFO/-/issues
Keywords: workbench,wxPython,GUI
Platform: WIN32
Platform: WIN64
Platform: OSX
Platform: POSIX
Classifier: Development Status :: 4 - Beta
Classifier: License :: OSI Approved :: MIT License
Classifier: Operating System :: MacOS
Classifier: Operating System :: Microsoft :: Windows
Classifier: Operating System :: POSIX
Classifier: Environment :: MacOS X :: Cocoa
Classifier: Environment :: Win32 (MS Windows)
Classifier: Environment :: X11 Applications :: GTK
Classifier: Programming Language :: Python :: 3
Classifier: Programming Language :: Python :: 3.10
Classifier: Programming Language :: Python :: 3.11
Classifier: Programming Language :: Python :: 3.12
Classifier: Programming Language :: Python :: 3.13
Classifier: Programming Language :: Python :: Implementation :: CPython
Classifier: Intended Audience :: Developers
Classifier: Topic :: Software Development :: Libraries
Classifier: Topic :: Software Development :: User Interfaces
Classifier: Topic :: Text Processing :: Fonts
Classifier: Topic :: Multimedia :: Graphics
Requires-Python: >=3.10
License-File: LICENSE
Requires-Dist: wbBase>=0.2.9
Requires-Dist: wbDefcon>=0.2.4
Requires-Dist: wbFontParts>=0.2.4
Requires-Dist: ufo2ft>=3.2.1
Requires-Dist: fs>=2.4.11
Requires-Dist: ufo-extractor>=0.8
Requires-Dist: vfbLib>=0.10
Dynamic: license-file
